{
	"def": 0,
	"sel": [
		{
			"string": "miscellaneous_fieldwarning",
			"desc": "miscellaneous_fieldwarning_desc",
			"type": "switch",
			"property": "set_session_fieldwarning",
			"list": "set_session_fieldwarning",
			"onstate": "#ffff",
			"offstate": "#fff2"
		},
		{
			"string": "miscellaneous_background",
			"desc": "miscellaneous_background_desc",
			"type": "range_list_specific",
			"property": "set_global_bgtype",
			"list": "set_global_bgtype",
			"onstate": "#ffff",
			"offstate": "#fff2",
			"is_default": true
		},
		{
			"string": "miscellaneous_tmb",
			"desc": "miscellaneous_tmb_desc",
			"type": "switch",
			"property": "set_global_toggle_mobilebuttons",
			"list": "set_global_toggle_mobilebuttons",
			"onstate": "#ffff",
			"offstate": "#fff2",
			"is_default": false
		}
	],
	"title": "miscellaneous_title",
	"name": "misc",
	"background": {
		"type": "rgba",
		"color": "#0F0F"
	}
}